rapidhrv/__init__.py
rapidhrv/analysis.py
rapidhrv/data.py
rapidhrv/preprocessing.py
rapidhrv/visualization.py
rapidhrv-0.2.7.dist-info/LICENSE
rapidhrv-0.2.7.dist-info/METADATA
rapidhrv-0.2.7.dist-info/WHEEL
rapidhrv-0.2.7.dist-info/RECORD
