Metadata-Version: 2.3
Name: rapidhrv
Version: 0.2.7
Summary: A package for preprocessing, analyzing and visualizing cardiac data
License: MIT
Author: Peter Kirk
Author-email: p.kirk@ucl.ac.uk
Requires-Python: >=3.11,<3.13
Classifier: License :: OSI Approved :: MIT License
Classifier: Programming Language :: Python :: 3
Classifier: Programming Language :: Python :: 3.11
Classifier: Programming Language :: Python :: 3.12
Provides-Extra: notebooks
Requires-Dist: dash (>=3.2.0,<4.0.0)
Requires-Dist: h5py (>=3.3.0,<4.0.0)
Requires-Dist: jupyter (>=1.0.0,<2.0.0) ; extra == "notebooks"
Requires-Dist: matplotlib (>=3.4.2,<4.0.0) ; extra == "notebooks"
Requires-Dist: numpy (>=2.3.2,<3.0.0)
Requires-Dist: pandas (>=2.3.2,<3.0.0)
Requires-Dist: scikit-learn (>=1.7.1,<2.0.0)
Requires-Dist: scipy (>=1.16.1,<2.0.0)
